intersight_auth/__init__.py
intersight_auth/exceptions.py
intersight_auth/intersight_auth.py
intersight_auth/intersight_auth_config.py
intersight_auth/oauth.py
intersight_auth/signing.py
intersight_auth-0.3.3.dist-info/METADATA
intersight_auth-0.3.3.dist-info/WHEEL
intersight_auth-0.3.3.dist-info/RECORD
