Metadata-Version: 2.3
Name: intersight-auth
Version: 0.3.3
Summary: Intersight Authentication helper for requests
Author: Chris Gascoigne
Author-email: cgascoig@cisco.com
Requires-Python: >=3.9.2
Classifier: Programming Language :: Python :: 3
Classifier: Programming Language :: Python :: 3.10
Classifier: Programming Language :: Python :: 3.11
Classifier: Programming Language :: Python :: 3.12
Classifier: Programming Language :: Python :: 3.13
Requires-Dist: cryptography (>37.0.2)
Requires-Dist: oauthlib (>=3.2.2,<4.0.0)
Requires-Dist: requests (>=2.27.1,<3.0.0)
Project-URL: Repository, https://github.com/cgascoig/intersight-auth
